{"cameraMode":{"drawMode":0,"name":"Shaded","section":"Shading Mode"},"sceneLighting":true,"audioPlay":false,"sceneViewState":{"m_AlwaysRefresh":false,"showFog":true,"showSkybox":true,"showFlares":true,"showImageEffects":true,"showParticleSystems":true,"showVisualEffectGraphs":true,"m_FxEnabled":true},"in2DMode":false,"pivot":{"x":-35.175018310546878,"y":-74.13780975341797,"z":-5.668368339538574},"rotation":{"x":-0.39449939131736758,"y":0.5726101994514465,"z":-0.36492928862571719,"w":-0.6192365884780884},"size":53.121665954589847,"orthographic":false}